envhub/__init__.py
envhub/__main__.py
envhub/add.py
envhub/auth.py
envhub/clone.py
envhub/decrypt.py
envhub/decrypt_and_store.py
envhub/decrypt_prod_by_api_key.py
envhub/pull.py
envhub/reset.py
envhub/services/createEnvVersion.py
envhub/services/getCurrentEnvVariables.py
envhub/services/getCurrentUserRole.py
envhub/services/getEncryptedProjectPassword.py
envhub/services/getProjectPassword.py
envhub/services/getSubscriptionLimitsForProject.py
envhub/services/get_env_vars_by_api_key_rpc.py
envhub/utils/crypto.py
envhub/utils/getEncryptedPasswordData.py
envhub/utils/getPassword.py
envhub/utils/getProjectId.py
envhub/utils/getRole.py
envhub/utils/passwordUtils.py
envhub_cli-0.6.1.dist-info/METADATA
envhub_cli-0.6.1.dist-info/WHEEL
envhub_cli-0.6.1.dist-info/entry_points.txt
envhub_cli-0.6.1.dist-info/licenses/LICENSE
envhub_cli-0.6.1.dist-info/RECORD
