Metadata-Version: 2.4
Name: envhub-cli
Version: 0.6.1
Summary: A CLI tool for managing environment variables with encryption and role-based access control
Project-URL: Homepage, https://github.com/Okaymisba/EnvHub-CLI
Project-URL: Bug Tracker, https://github.com/Okaymisba/EnvHub-CLI/issues
Author-email: Misbah Sarfaraz <msbahsarfaraz@gmail.com>
License: Mozilla Public License 2.0
License-File: LICENSE
Keywords: cli,encryption,envhub,environment-variables,sharing env,supabase
Classifier: Development Status :: 3 - Alpha
Classifier: Intended Audience :: Developers
Classifier: License :: OSI Approved :: Mozilla Public License 2.0 (MPL 2.0)
Classifier: Programming Language :: Python :: 3.8
Classifier: Programming Language :: Python :: 3.9
Classifier: Programming Language :: Python :: 3.10
Classifier: Programming Language :: Python :: 3.11
Classifier: Topic :: Software Development :: Libraries :: Python Modules
Classifier: Topic :: Utilities
Requires-Python: >=3.8
Requires-Dist: cryptography~=45.0.4
Requires-Dist: packaging~=25.0
Requires-Dist: python-dotenv~=1.1.0
Requires-Dist: requests~=2.32.4
Requires-Dist: supabase~=2.15.3
Requires-Dist: typer[all]~=0.16.0
